rest_framework_idempotency_key/__init__.py
rest_framework_idempotency_key/__version__.py
rest_framework_idempotency_key/apps.py
rest_framework_idempotency_key/decorators.py
rest_framework_idempotency_key/middleware.py
rest_framework_idempotency_key/models.py
rest_framework_idempotency_key/utils.py
rest_framework_idempotency_key/migrations/0001_initial.py
rest_framework_idempotency_key/migrations/0002_alter_idempotencykey_user.py
rest_framework_idempotency_key/migrations/0003_remove_user.py
rest_framework_idempotency_key/migrations/__init__.py
djangorestframework_idempotency_key-1.0.3.dist-info/LICENSE
djangorestframework_idempotency_key-1.0.3.dist-info/METADATA
djangorestframework_idempotency_key-1.0.3.dist-info/WHEEL
djangorestframework_idempotency_key-1.0.3.dist-info/top_level.txt
djangorestframework_idempotency_key-1.0.3.dist-info/RECORD
