Metadata-Version: 2.1
Name: djangorestframework-idempotency-key
Version: 1.0.3
Summary: Idempotency key app & middleware for Django Rest Framework
Home-page: https://github.com/hardcoretech/djangorestframework-idempotency-key
Author: xeonchen, kilikkuo
Author-email: pypi@hardcoretech.co
Project-URL: Changelog, https://github.com/hardcoretech/djangorestframework-idempotency-key/blob/main/CHANGELOG.md
Classifier: Programming Language :: Python :: 3
Classifier: License :: OSI Approved :: MIT License
Classifier: Operating System :: OS Independent
Requires-Python: >=3.6
License-File: LICENSE
Requires-Dist: django
Requires-Dist: djangorestframework
Requires-Dist: data-spec-validator >=1.2.0
